<?xml version="1.0" encoding="GB2312" standalone="no"?>
<dataset create-date="null" creator="null" flag="0" modifier="null" modify-date="null" name="lbLiveBOSLogQuery" object-id="null" package="系统管理" type="24" version="null">
    <describe>系统日志查询</describe>
    <comment/>
    <attribute>256</attribute>
    <class>com.apex.livebos.bean.LiveBOSLogBean</class>
    <parameters/>
    <display-options>
        <commands>
            <command type="2">
                <describe>导出</describe>
                <define>
                    <item>lbLiveBOSLogQuery</item>
                    <item>ToExcel</item>
                </define>
                <is-default>2</is-default>
                <attribute>0</attribute>
                <icon-cls/>
                <tip/>
            </command>
            <command type="2">
                <describe>打印</describe>
                <define>
                    <item>lbLiveBOSLogQuery</item>
                    <item>Print</item>
                </define>
                <is-default>2</is-default>
                <attribute>0</attribute>
                <icon-cls/>
                <tip/>
            </command>
        </commands>
        <relations/>
    </display-options>
    <properties/>
    <orders/>
    <extend-buttons/>
</dataset>
