<?xml version="1.0" encoding="GB2312" standalone="no"?>
<object create-date="null" creator="null" flag="1" modifier="null" modify-date="null" name="lbReportPublishSchedule" object-id="89EC9706D7EF4065A97798DC4BFE39C9" package="系统管理" type="0" version="V1.1">
    <describe>报表分发任务</describe>
    <comment/>
    <datasource-name/>
    <parent/>
    <attribute>134217984</attribute>
    <templet>ReportPublishSchedule</templet>
    <columns>
        <column>
            <name>ID</name>
            <describe>ID</describe>
            <type>1</type>
            <biz-type>200</biz-type>
            <length>12</length>
            <scale>0</scale>
            <control>0</control>
            <primary-property>2</primary-property>
            <nullable>true</nullable>
            <unique>false</unique>
            <enabled>true</enabled>
            <visible>true</visible>
            <option/>
            <meta-column/>
            <ref-object/>
            <default/>
            <attribute>1</attribute>
            <order-direction>0</order-direction>
            <expression/>
            <invisible-expression/>
            <disable-expression/>
            <category/>
            <fire-event>0</fire-event>
            <check-type>0</check-type>
            <real-type>0</real-type>
            <comment/>
            <validation/>
            <scope-permissions/>
        </column>
        <column>
            <name>ReportName</name>
            <describe>报表名</describe>
            <type>0</type>
            <biz-type>100</biz-type>
            <length>200</length>
            <scale>0</scale>
            <control>0</control>
            <primary-property>0</primary-property>
            <nullable>true</nullable>
            <unique>false</unique>
            <enabled>true</enabled>
            <visible>true</visible>
            <option/>
            <meta-column/>
            <ref-object/>
            <default/>
            <attribute>0</attribute>
            <order-direction>0</order-direction>
            <expression/>
            <invisible-expression/>
            <disable-expression/>
            <category/>
            <fire-event>0</fire-event>
            <check-type>0</check-type>
            <real-type>0</real-type>
            <comment/>
            <validation/>
            <scope-permissions/>
        </column>
        <column>
            <name>ExportType</name>
            <describe>报表类型</describe>
            <type>0</type>
            <biz-type>100</biz-type>
            <length>10</length>
            <scale>0</scale>
            <control>5</control>
            <primary-property>4</primary-property>
            <nullable>false</nullable>
            <unique>false</unique>
            <enabled>true</enabled>
            <visible>true</visible>
            <option>PDF|PDF文件;EXCEL|Excel文件;RTF|Word文件</option>
            <meta-column/>
            <ref-object/>
            <default>PDF</default>
            <attribute>0</attribute>
            <order-direction>0</order-direction>
            <expression/>
            <invisible-expression/>
            <disable-expression/>
            <category/>
            <fire-event>0</fire-event>
            <check-type>0</check-type>
            <real-type>0</real-type>
            <comment/>
            <validation/>
            <scope-permissions/>
        </column>
        <column>
            <name>Subject</name>
            <describe>报表主题</describe>
            <type>0</type>
            <biz-type>100</biz-type>
            <length>300</length>
            <scale>0</scale>
            <control>1</control>
            <primary-property>4</primary-property>
            <nullable>false</nullable>
            <unique>false</unique>
            <enabled>true</enabled>
            <visible>true</visible>
            <option/>
            <meta-column/>
            <ref-object/>
            <default/>
            <attribute>2</attribute>
            <order-direction>0</order-direction>
            <expression/>
            <invisible-expression/>
            <disable-expression/>
            <category/>
            <fire-event>0</fire-event>
            <check-type>0</check-type>
            <real-type>0</real-type>
            <comment/>
            <validation/>
            <scope-permissions/>
        </column>
        <column>
            <name>RunTime</name>
            <describe>执行时间</describe>
            <type>18</type>
            <biz-type>304</biz-type>
            <length>0</length>
            <scale>0</scale>
            <control>29</control>
            <primary-property>4</primary-property>
            <nullable>false</nullable>
            <unique>false</unique>
            <enabled>true</enabled>
            <visible>true</visible>
            <option/>
            <meta-column/>
            <ref-object/>
            <default/>
            <attribute>0</attribute>
            <order-direction>0</order-direction>
            <expression/>
            <invisible-expression/>
            <disable-expression/>
            <category/>
            <fire-event>0</fire-event>
            <check-type>0</check-type>
            <real-type>0</real-type>
            <comment/>
            <validation/>
            <scope-permissions/>
        </column>
        <column>
            <name>Periodicity</name>
            <describe>分发周期</describe>
            <type>7</type>
            <biz-type>400</biz-type>
            <length>0</length>
            <scale>0</scale>
            <control>5</control>
            <primary-property>4</primary-property>
            <nullable>false</nullable>
            <unique>false</unique>
            <enabled>true</enabled>
            <visible>true</visible>
            <option>1|每天;2|每周;3|每月;0|一次性</option>
            <meta-column/>
            <ref-object/>
            <default>1</default>
            <attribute>0</attribute>
            <order-direction>0</order-direction>
            <expression/>
            <invisible-expression/>
            <disable-expression/>
            <category/>
            <fire-event>1</fire-event>
            <check-type>0</check-type>
            <real-type>0</real-type>
            <comment/>
            <validation/>
            <scope-permissions/>
        </column>
        <column>
            <name>DayStart</name>
            <describe>开始日期</describe>
            <type>3</type>
            <biz-type>300</biz-type>
            <length>0</length>
            <scale>0</scale>
            <control>3</control>
            <primary-property>4</primary-property>
            <nullable>false</nullable>
            <unique>false</unique>
            <enabled>true</enabled>
            <visible>true</visible>
            <option/>
            <meta-column/>
            <ref-object/>
            <default>$DateTime.Today</default>
            <attribute>0</attribute>
            <order-direction>0</order-direction>
            <expression/>
            <invisible-expression/>
            <disable-expression/>
            <category>每天详情</category>
            <fire-event>0</fire-event>
            <check-type>0</check-type>
            <real-type>0</real-type>
            <comment/>
            <validation/>
            <scope-permissions/>
        </column>
        <column>
            <name>DayOption</name>
            <describe>天选项</describe>
            <type>7</type>
            <biz-type>400</biz-type>
            <length>0</length>
            <scale>0</scale>
            <control>5</control>
            <primary-property>4</primary-property>
            <nullable>false</nullable>
            <unique>false</unique>
            <enabled>true</enabled>
            <visible>true</visible>
            <option>1|每天;2|每周工作日;3|间隔几天</option>
            <meta-column/>
            <ref-object/>
            <default>1</default>
            <attribute>0</attribute>
            <order-direction>0</order-direction>
            <expression/>
            <invisible-expression/>
            <disable-expression/>
            <category>每天详情</category>
            <fire-event>1</fire-event>
            <check-type>0</check-type>
            <real-type>0</real-type>
            <comment/>
            <validation/>
            <scope-permissions/>
        </column>
        <column>
            <name>DayInterval</name>
            <describe>每几天</describe>
            <type>1</type>
            <biz-type>200</biz-type>
            <length>3</length>
            <scale>0</scale>
            <control>1</control>
            <primary-property>4</primary-property>
            <nullable>false</nullable>
            <unique>false</unique>
            <enabled>true</enabled>
            <visible>true</visible>
            <option/>
            <meta-column/>
            <ref-object/>
            <default>1</default>
            <attribute>0</attribute>
            <order-direction>0</order-direction>
            <expression/>
            <invisible-expression/>
            <disable-expression/>
            <category>每天详情</category>
            <fire-event>0</fire-event>
            <check-type>0</check-type>
            <real-type>0</real-type>
            <comment/>
            <validation/>
            <scope-permissions/>
        </column>
        <column>
            <name>WeekInterval</name>
            <describe>每几周</describe>
            <type>1</type>
            <biz-type>200</biz-type>
            <length>2</length>
            <scale>0</scale>
            <control>1</control>
            <primary-property>0</primary-property>
            <nullable>true</nullable>
            <unique>false</unique>
            <enabled>true</enabled>
            <visible>true</visible>
            <option/>
            <meta-column/>
            <ref-object/>
            <default>1</default>
            <attribute>0</attribute>
            <order-direction>0</order-direction>
            <expression/>
            <invisible-expression/>
            <disable-expression/>
            <category>每周详情</category>
            <fire-event>0</fire-event>
            <check-type>0</check-type>
            <real-type>0</real-type>
            <comment/>
            <validation/>
            <scope-permissions/>
        </column>
        <column>
            <name>WeekLimit</name>
            <describe>星期限制</describe>
            <type>15</type>
            <biz-type>401</biz-type>
            <length>0</length>
            <scale>0</scale>
            <control>4</control>
            <primary-property>0</primary-property>
            <nullable>true</nullable>
            <unique>false</unique>
            <enabled>true</enabled>
            <visible>true</visible>
            <option>2|星期一;3|星期二;4|星期三;5|星期四;6|星期五;7|星期六;1|星期日</option>
            <meta-column/>
            <ref-object/>
            <default/>
            <attribute>0</attribute>
            <order-direction>0</order-direction>
            <expression/>
            <invisible-expression/>
            <disable-expression/>
            <category>每周详情</category>
            <fire-event>0</fire-event>
            <check-type>0</check-type>
            <real-type>0</real-type>
            <comment/>
            <validation/>
            <scope-permissions/>
        </column>
        <column>
            <name>MonthOption</name>
            <describe>月选项</describe>
            <type>7</type>
            <biz-type>400</biz-type>
            <length>0</length>
            <scale>0</scale>
            <control>2</control>
            <primary-property>4</primary-property>
            <nullable>false</nullable>
            <unique>false</unique>
            <enabled>true</enabled>
            <visible>true</visible>
            <option>1|按天;2|按星期</option>
            <meta-column/>
            <ref-object/>
            <default>1</default>
            <attribute>0</attribute>
            <order-direction>0</order-direction>
            <expression/>
            <invisible-expression/>
            <disable-expression/>
            <category>每月详情</category>
            <fire-event>1</fire-event>
            <check-type>0</check-type>
            <real-type>0</real-type>
            <comment/>
            <validation/>
            <scope-permissions/>
        </column>
        <column>
            <name>MonthDay</name>
            <describe>每月第几天</describe>
            <type>1</type>
            <biz-type>200</biz-type>
            <length>2</length>
            <scale>0</scale>
            <control>1</control>
            <primary-property>4</primary-property>
            <nullable>false</nullable>
            <unique>false</unique>
            <enabled>true</enabled>
            <visible>true</visible>
            <option/>
            <meta-column/>
            <ref-object/>
            <default>1</default>
            <attribute>0</attribute>
            <order-direction>0</order-direction>
            <expression/>
            <invisible-expression/>
            <disable-expression/>
            <category>每月详情</category>
            <fire-event>0</fire-event>
            <check-type>0</check-type>
            <real-type>0</real-type>
            <comment/>
            <validation/>
            <scope-permissions/>
        </column>
        <column>
            <name>MonthWeek1</name>
            <describe>每月第几星期</describe>
            <type>7</type>
            <biz-type>400</biz-type>
            <length>0</length>
            <scale>0</scale>
            <control>2</control>
            <primary-property>0</primary-property>
            <nullable>true</nullable>
            <unique>false</unique>
            <enabled>true</enabled>
            <visible>true</visible>
            <option>1|第一个;2|第二个;3|第三个;4|第四个;5|最后一个</option>
            <meta-column/>
            <ref-object/>
            <default>1</default>
            <attribute>0</attribute>
            <order-direction>0</order-direction>
            <expression/>
            <invisible-expression/>
            <disable-expression/>
            <category>每月详情</category>
            <fire-event>0</fire-event>
            <check-type>0</check-type>
            <real-type>0</real-type>
            <comment/>
            <validation/>
            <scope-permissions/>
        </column>
        <column>
            <name>MonthWeek2</name>
            <describe>星期选择</describe>
            <type>7</type>
            <biz-type>400</biz-type>
            <length>0</length>
            <scale>0</scale>
            <control>2</control>
            <primary-property>4</primary-property>
            <nullable>false</nullable>
            <unique>false</unique>
            <enabled>true</enabled>
            <visible>true</visible>
            <option>2|星期一;3|星期二;4|星期三;5|星期四;6|星期五;7|星期六;1|星期日</option>
            <meta-column/>
            <ref-object/>
            <default>2</default>
            <attribute>0</attribute>
            <order-direction>0</order-direction>
            <expression/>
            <invisible-expression/>
            <disable-expression/>
            <category>每月详情</category>
            <fire-event>0</fire-event>
            <check-type>0</check-type>
            <real-type>0</real-type>
            <comment/>
            <validation/>
            <scope-permissions/>
        </column>
        <column>
            <name>MonthLimit</name>
            <describe>月份限制</describe>
            <type>15</type>
            <biz-type>401</biz-type>
            <length>0</length>
            <scale>0</scale>
            <control>4</control>
            <primary-property>0</primary-property>
            <nullable>true</nullable>
            <unique>false</unique>
            <enabled>true</enabled>
            <visible>true</visible>
            <option>1|一月;2|二月;3|三月;4|四月;5|五月;6|六月;7|七月;8|八月;9|九月;10|十月;11|十一月;12|十二月</option>
            <meta-column/>
            <ref-object/>
            <default/>
            <attribute>0</attribute>
            <order-direction>0</order-direction>
            <expression/>
            <invisible-expression/>
            <disable-expression/>
            <category>每月详情</category>
            <fire-event>0</fire-event>
            <check-type>0</check-type>
            <real-type>0</real-type>
            <comment/>
            <validation/>
            <scope-permissions/>
        </column>
        <column>
            <name>OnceDayStart</name>
            <describe>执行日期</describe>
            <type>3</type>
            <biz-type>300</biz-type>
            <length>0</length>
            <scale>0</scale>
            <control>3</control>
            <primary-property>0</primary-property>
            <nullable>true</nullable>
            <unique>false</unique>
            <enabled>true</enabled>
            <visible>true</visible>
            <option/>
            <meta-column/>
            <ref-object/>
            <default>$DateTime.Today</default>
            <attribute>0</attribute>
            <order-direction>0</order-direction>
            <expression/>
            <invisible-expression/>
            <disable-expression/>
            <category>一次性信息</category>
            <fire-event>0</fire-event>
            <check-type>0</check-type>
            <real-type>0</real-type>
            <comment/>
            <validation/>
            <scope-permissions/>
        </column>
        <column>
            <name>SubscribeEmail</name>
            <describe>接收邮件列表</describe>
            <type>0</type>
            <biz-type>100</biz-type>
            <length>2000</length>
            <scale>0</scale>
            <control>1</control>
            <primary-property>0</primary-property>
            <nullable>true</nullable>
            <unique>false</unique>
            <enabled>true</enabled>
            <visible>true</visible>
            <option/>
            <meta-column/>
            <ref-object/>
            <default/>
            <attribute>0</attribute>
            <order-direction>0</order-direction>
            <expression/>
            <invisible-expression/>
            <disable-expression/>
            <category>分发信息</category>
            <fire-event>0</fire-event>
            <check-type>0</check-type>
            <real-type>0</real-type>
            <comment/>
            <validation/>
            <scope-permissions/>
        </column>
        <column>
            <name>SubscribeUser</name>
            <describe>目标文件夹</describe>
            <type>16</type>
            <biz-type>600</biz-type>
            <length>0</length>
            <scale>0</scale>
            <control>25</control>
            <primary-property>0</primary-property>
            <nullable>true</nullable>
            <unique>false</unique>
            <enabled>true</enabled>
            <visible>true</visible>
            <option/>
            <meta-column/>
            <ref-object>tUser</ref-object>
            <default/>
            <attribute>0</attribute>
            <order-direction>0</order-direction>
            <expression/>
            <invisible-expression/>
            <disable-expression/>
            <category>分发信息</category>
            <fire-event>0</fire-event>
            <check-type>0</check-type>
            <real-type>0</real-type>
            <comment/>
            <validation/>
            <scope-permissions/>
        </column>
        <column>
            <name>SubscribeOwner</name>
            <describe>订阅人</describe>
            <type>6</type>
            <biz-type>500</biz-type>
            <length>9</length>
            <scale>0</scale>
            <control>10</control>
            <primary-property>5</primary-property>
            <nullable>true</nullable>
            <unique>false</unique>
            <enabled>false</enabled>
            <visible>true</visible>
            <option/>
            <meta-column/>
            <ref-object>tUser</ref-object>
            <default>$Login.User</default>
            <attribute>0</attribute>
            <order-direction>0</order-direction>
            <expression/>
            <invisible-expression/>
            <disable-expression/>
            <category>分发信息</category>
            <fire-event>0</fire-event>
            <check-type>0</check-type>
            <real-type>0</real-type>
            <comment/>
            <validation/>
            <scope-permissions/>
        </column>
        <column>
            <name>Parameter</name>
            <describe>参数信息</describe>
            <type>0</type>
            <biz-type>100</biz-type>
            <length>2000</length>
            <scale>0</scale>
            <control>0</control>
            <primary-property>0</primary-property>
            <nullable>true</nullable>
            <unique>false</unique>
            <enabled>true</enabled>
            <visible>true</visible>
            <option/>
            <meta-column/>
            <ref-object/>
            <default/>
            <attribute>0</attribute>
            <order-direction>0</order-direction>
            <expression/>
            <invisible-expression/>
            <disable-expression/>
            <category>分发信息</category>
            <fire-event>0</fire-event>
            <check-type>0</check-type>
            <real-type>0</real-type>
            <comment/>
            <validation/>
            <scope-permissions/>
        </column>
    </columns>
    <display-options>
        <commands>
            <command type="2">
                <describe>查看</describe>
                <define>
                    <item>lbReportPublishSchedule</item>
                    <item>View</item>
                </define>
                <is-default>2</is-default>
                <attribute>0</attribute>
                <icon-cls/>
                <tip/>
            </command>
            <command type="2">
                <describe>新增</describe>
                <define>
                    <item>lbReportPublishSchedule</item>
                    <item>Add</item>
                </define>
                <is-default>2</is-default>
                <attribute>0</attribute>
                <icon-cls/>
                <tip/>
            </command>
            <command type="2">
                <describe>删除</describe>
                <define>
                    <item>lbReportPublishSchedule</item>
                    <item>Delete</item>
                </define>
                <is-default>2</is-default>
                <attribute>0</attribute>
                <icon-cls/>
                <tip/>
            </command>
            <command type="2">
                <describe>修改</describe>
                <define>
                    <item>lbReportPublishSchedule</item>
                    <item>Update</item>
                </define>
                <is-default>1</is-default>
                <attribute>0</attribute>
                <icon-cls/>
                <tip/>
            </command>
            <command type="2">
                <describe>导入</describe>
                <define>
                    <item>lbReportPublishSchedule</item>
                    <item>LoadExcel</item>
                </define>
                <is-default>2</is-default>
                <attribute>0</attribute>
                <icon-cls/>
                <tip/>
            </command>
            <command type="2">
                <describe>统计</describe>
                <define>
                    <item>lbReportPublishSchedule</item>
                    <item>Compute</item>
                </define>
                <is-default>2</is-default>
                <attribute>0</attribute>
                <icon-cls/>
                <tip/>
            </command>
            <command type="2">
                <describe>导出</describe>
                <define>
                    <item>lbReportPublishSchedule</item>
                    <item>ToExcel</item>
                </define>
                <is-default>2</is-default>
                <attribute>0</attribute>
                <icon-cls/>
                <tip/>
            </command>
            <command type="2">
                <describe>打印</describe>
                <define>
                    <item>lbReportPublishSchedule</item>
                    <item>Print</item>
                </define>
                <is-default>2</is-default>
                <attribute>0</attribute>
                <icon-cls/>
                <tip/>
            </command>
        </commands>
        <relations/>
    </display-options>
    <subdivisions/>
    <methods/>
    <properties/>
    <orders/>
    <panels/>
    <extend-buttons/>
</object>
