<?xml version="1.0" encoding="GB2312" standalone="no"?>
<object create-date="2017.08.31 10:39:14" creator="zhong.apex" flag="0" name="vIB_ZDZCCZFKHFLCB_M" object-id="4f8df200-ebd2-4d85-a15f-15922c92a9b9" package="100_新三板.持续督导阶段.04-重大资产重组反馈回复流程" type="1" version="1.0">
    <describe>我发起的重大资产重组反馈回复流程</describe>
    <datasource-name>ECIF</datasource-name>
    <parent>lcIB_ZDZCCZFKHFLCB</parent>
    <attribute>268437520</attribute>
    <templet>默认</templet>
    <parameters/>
    <columns>
        <column>
            <name>ID</name>
            <describe>ID</describe>
            <type>8</type>
            <biz-type>200</biz-type>
            <length>16</length>
            <scale>0</scale>
            <control>0</control>
            <primary-property>2</primary-property>
            <nullable>false</nullable>
            <unique>false</unique>
            <enabled>false</enabled>
            <visible>false</visible>
            <option/>
            <meta-column/>
            <ref-object/>
            <default/>
            <attribute>0</attribute>
            <order-direction>0</order-direction>
            <expression/>
            <invisible-expression/>
            <disable-expression/>
            <category/>
            <fire-event>0</fire-event>
            <check-type>0</check-type>
            <real-type>1</real-type>
            <comment/>
            <validation/>
            <scope-permissions/>
            <properties/>
        </column>
        <column>
            <name>SQR</name>
            <describe>申请人</describe>
            <type>8</type>
            <biz-type>500</biz-type>
            <length>12</length>
            <scale>0</scale>
            <control>10</control>
            <primary-property>0</primary-property>
            <nullable>true</nullable>
            <unique>false</unique>
            <enabled>false</enabled>
            <visible>true</visible>
            <option/>
            <meta-column/>
            <ref-object>tUser</ref-object>
            <default>$Login.User</default>
            <attribute>0</attribute>
            <order-direction>0</order-direction>
            <expression/>
            <invisible-expression/>
            <disable-expression/>
            <category>申请人信息</category>
            <fire-event>1</fire-event>
            <check-type>0</check-type>
            <real-type>6</real-type>
            <comment/>
            <validation/>
            <scope-permissions/>
            <properties/>
        </column>
        <column>
            <name>SQBM</name>
            <describe>申请部门</describe>
            <type>8</type>
            <biz-type>500</biz-type>
            <length>12</length>
            <scale>0</scale>
            <control>10</control>
            <primary-property>0</primary-property>
            <nullable>true</nullable>
            <unique>false</unique>
            <enabled>false</enabled>
            <visible>true</visible>
            <option/>
            <meta-column/>
            <ref-object>lbOrganization</ref-object>
            <default>$Login.User.OrgID</default>
            <attribute>0</attribute>
            <order-direction>0</order-direction>
            <expression/>
            <invisible-expression/>
            <disable-expression/>
            <category>申请人信息</category>
            <fire-event>0</fire-event>
            <check-type>0</check-type>
            <real-type>6</real-type>
            <comment/>
            <validation/>
            <scope-permissions/>
            <properties/>
        </column>
        <column>
            <name>SQSJ</name>
            <describe>申请时间</describe>
            <type>8</type>
            <biz-type>301</biz-type>
            <length>19</length>
            <scale>0</scale>
            <control>37</control>
            <primary-property>0</primary-property>
            <nullable>true</nullable>
            <unique>false</unique>
            <enabled>false</enabled>
            <visible>true</visible>
            <option/>
            <meta-column/>
            <ref-object/>
            <default>$DateTime.Now</default>
            <attribute>4</attribute>
            <order-direction>2</order-direction>
            <expression/>
            <invisible-expression/>
            <disable-expression/>
            <category>申请人信息</category>
            <fire-event>0</fire-event>
            <check-type>0</check-type>
            <real-type>3</real-type>
            <comment/>
            <validation/>
            <scope-permissions/>
            <properties/>
        </column>
        <column>
            <name>LCBH</name>
            <describe>流程编号</describe>
            <type>8</type>
            <biz-type>100</biz-type>
            <length>100</length>
            <scale>0</scale>
            <control>1</control>
            <primary-property>10</primary-property>
            <nullable>true</nullable>
            <unique>false</unique>
            <enabled>false</enabled>
            <visible>true</visible>
            <option/>
            <meta-column/>
            <ref-object/>
            <default/>
            <attribute>0</attribute>
            <order-direction>0</order-direction>
            <expression/>
            <invisible-expression/>
            <disable-expression/>
            <category>申请人信息</category>
            <fire-event>0</fire-event>
            <check-type>0</check-type>
            <real-type>0</real-type>
            <comment/>
            <validation/>
            <scope-permissions/>
            <properties/>
        </column>
        <column>
            <name>OLDBH</name>
            <describe>老系统编号</describe>
            <type>8</type>
            <biz-type>100</biz-type>
            <length>50</length>
            <scale>0</scale>
            <control>0</control>
            <primary-property>0</primary-property>
            <nullable>true</nullable>
            <unique>false</unique>
            <enabled>false</enabled>
            <visible>false</visible>
            <option/>
            <meta-column/>
            <ref-object/>
            <default/>
            <attribute>0</attribute>
            <order-direction>0</order-direction>
            <expression/>
            <invisible-expression/>
            <disable-expression/>
            <category>申请人信息</category>
            <fire-event>0</fire-event>
            <check-type>0</check-type>
            <real-type>0</real-type>
            <comment/>
            <validation/>
            <scope-permissions/>
            <properties/>
        </column>
        <column>
            <name>InstID</name>
            <describe>InstID</describe>
            <type>8</type>
            <biz-type>200</biz-type>
            <length>16</length>
            <scale>0</scale>
            <control>0</control>
            <primary-property>0</primary-property>
            <nullable>false</nullable>
            <unique>false</unique>
            <enabled>true</enabled>
            <visible>true</visible>
            <option/>
            <meta-column/>
            <ref-object/>
            <default/>
            <attribute>0</attribute>
            <order-direction>0</order-direction>
            <expression/>
            <invisible-expression/>
            <disable-expression/>
            <category/>
            <fire-event>0</fire-event>
            <check-type>0</check-type>
            <real-type>1</real-type>
            <comment/>
            <validation/>
            <scope-permissions/>
            <properties/>
        </column>
        <column>
            <name>LCBT</name>
            <describe>公文主题</describe>
            <type>8</type>
            <biz-type>100</biz-type>
            <length>500</length>
            <scale>0</scale>
            <control>1</control>
            <primary-property>0</primary-property>
            <nullable>false</nullable>
            <unique>false</unique>
            <enabled>false</enabled>
            <visible>true</visible>
            <option/>
            <meta-column/>
            <ref-object/>
            <default/>
            <attribute>4098</attribute>
            <order-direction>0</order-direction>
            <expression/>
            <invisible-expression/>
            <disable-expression/>
            <category>基本信息</category>
            <fire-event>0</fire-event>
            <check-type>0</check-type>
            <real-type>0</real-type>
            <comment/>
            <validation/>
            <scope-permissions/>
            <properties/>
        </column>
        <column>
            <name>GWZW</name>
            <describe>公文正文</describe>
            <type>8</type>
            <biz-type>100</biz-type>
            <length>4000</length>
            <scale>0</scale>
            <control>19</control>
            <primary-property>0</primary-property>
            <nullable>false</nullable>
            <unique>false</unique>
            <enabled>false</enabled>
            <visible>true</visible>
            <option/>
            <meta-column/>
            <ref-object/>
            <default/>
            <attribute>4096</attribute>
            <order-direction>0</order-direction>
            <expression/>
            <invisible-expression/>
            <disable-expression/>
            <category>基本信息</category>
            <fire-event>0</fire-event>
            <check-type>0</check-type>
            <real-type>0</real-type>
            <comment/>
            <validation/>
            <scope-permissions/>
            <properties/>
        </column>
        <column>
            <name>LDSP</name>
            <describe>重要领导意见</describe>
            <type>8</type>
            <biz-type>100</biz-type>
            <length>1000</length>
            <scale>0</scale>
            <control>16</control>
            <primary-property>8</primary-property>
            <nullable>true</nullable>
            <unique>false</unique>
            <enabled>false</enabled>
            <visible>true</visible>
            <option/>
            <meta-column/>
            <ref-object/>
            <default/>
            <attribute>4096</attribute>
            <order-direction>0</order-direction>
            <expression>&lt;%@ livebos language='javascript' %&gt;
var varSrc="/bss/ibb/nworkflow/page/suggestion.sdo?LcbdID="+ID+"&amp;Lcbd=lcIB_ZDZCCZFKHFLCB"+"&amp;Ywlx=110000";
"&lt;iframe id='lc_zyldyj' frameborder='0' width='100%' height='100%' scrolling='no' src='"+varSrc+"'&gt;&lt;/iframe&gt;" </expression>
            <invisible-expression>&lt;%@ livebos language='javascript' %&gt;
LB.getClient().isStandard==false</invisible-expression>
            <disable-expression/>
            <category>基本信息</category>
            <fire-event>0</fire-event>
            <check-type>0</check-type>
            <real-type>0</real-type>
            <comment/>
            <validation/>
            <scope-permissions/>
            <properties/>
        </column>
        <column>
            <name>BZ</name>
            <describe>备注</describe>
            <type>8</type>
            <biz-type>100</biz-type>
            <length>1000</length>
            <scale>0</scale>
            <control>7</control>
            <primary-property>0</primary-property>
            <nullable>true</nullable>
            <unique>false</unique>
            <enabled>false</enabled>
            <visible>true</visible>
            <option/>
            <meta-column/>
            <ref-object/>
            <default/>
            <attribute>4096</attribute>
            <order-direction>0</order-direction>
            <expression/>
            <invisible-expression/>
            <disable-expression/>
            <category>基本信息</category>
            <fire-event>0</fire-event>
            <check-type>0</check-type>
            <real-type>0</real-type>
            <comment/>
            <validation/>
            <scope-permissions/>
            <properties/>
        </column>
        <column>
            <name>XMMC</name>
            <describe>项目名称</describe>
            <type>8</type>
            <biz-type>500</biz-type>
            <length>16</length>
            <scale>0</scale>
            <control>10</control>
            <primary-property>0</primary-property>
            <nullable>false</nullable>
            <unique>false</unique>
            <enabled>false</enabled>
            <visible>true</visible>
            <option/>
            <meta-column/>
            <ref-object>VIB_XMXX_XSB_WD</ref-object>
            <default/>
            <attribute>67108864</attribute>
            <order-direction>0</order-direction>
            <expression/>
            <invisible-expression/>
            <disable-expression/>
            <category>基本信息</category>
            <fire-event>1</fire-event>
            <check-type>0</check-type>
            <real-type>6</real-type>
            <comment/>
            <validation/>
            <constraint type="3">
                <SQL>["KPJD IN (112,113)\r\nAND NOT EXISTS (SELECT 1 FROM ECIF.lcIB_DZQZLCB T,JGCRM.OS_WFENTRY WF\r\n                WHERE XMMC = tIB_XMXX_XSB.ID \r\n\t\t\t\t  AND WF.ID = T.INSTID\r\n\t\t\t\t  AND WF.STATE = 1\r\n\t\t\t\t\t\t\t\t  )\r\nAND NOT EXISTS (SELECT 1 FROM ECIF.lcIB_DZFKHFLCB T,JGCRM.OS_WFENTRY WF\r\n                WHERE XMMC = tIB_XMXX_XSB.ID \r\n\t\t\t\t  AND WF.ID = T.INSTID\r\n\t\t\t\t  AND WF.STATE = 1)\r\nAND NOT EXISTS (SELECT 1 FROM ECIF.lcIB_ZDZCCZSBQZLCB T,JGCRM.OS_WFENTRY WF\r\n                WHERE XMMC = tIB_XMXX_XSB.ID \r\n\t\t\t\t  AND WF.ID = T.INSTID\r\n\t\t\t\t  AND WF.STATE = 1)",[]]</SQL>
                <refColumns/>
            </constraint>
            <scope-permissions/>
            <properties/>
        </column>
        <column>
            <name>SM</name>
            <describe>说明</describe>
            <type>8</type>
            <biz-type>100</biz-type>
            <length>200</length>
            <scale>0</scale>
            <control>16</control>
            <primary-property>8</primary-property>
            <nullable>true</nullable>
            <unique>false</unique>
            <enabled>true</enabled>
            <visible>true</visible>
            <default/>
            <attribute>266240</attribute>
            <order-direction>0</order-direction>
            <expression>&lt;%@ livebos language='javascript' %&gt;
'&lt;font color="red"&gt;&lt;b&gt;该项目为风险项目，请高度关注&lt;/b&gt;&lt;/font&gt;'&#13;
</expression>
            <invisible-expression>&lt;%@ livebos language='javascript' %&gt;
XMMC.SFFXXM!=1</invisible-expression>
            <category>基本信息</category>
            <fire-event>1</fire-event>
            <check-type>0</check-type>
            <real-type>0</real-type>
            <properties/>
        </column>
        <column>
            <name>KHQC</name>
            <describe>公司名称</describe>
            <type>8</type>
            <biz-type>500</biz-type>
            <length>0</length>
            <scale>0</scale>
            <control>10</control>
            <primary-property>0</primary-property>
            <nullable>true</nullable>
            <unique>false</unique>
            <enabled>false</enabled>
            <visible>true</visible>
            <option/>
            <meta-column/>
            <ref-object>tIB_KHXX</ref-object>
            <default/>
            <attribute>0</attribute>
            <order-direction>0</order-direction>
            <invisible-expression/>
            <disable-expression/>
            <category>基本信息</category>
            <fire-event>0</fire-event>
            <check-type>0</check-type>
            <real-type>6</real-type>
            <comment/>
            <validation/>
            <scope-permissions/>
            <properties/>
        </column>
        <column>
            <name>SSXT</name>
            <describe>所属系统</describe>
            <type>8</type>
            <biz-type>400</biz-type>
            <length>0</length>
            <scale>0</scale>
            <control>2</control>
            <primary-property>0</primary-property>
            <nullable>true</nullable>
            <unique>false</unique>
            <enabled>false</enabled>
            <visible>true</visible>
            <option>$D{IB_XMSSFZ}</option>
            <meta-column/>
            <ref-object/>
            <default/>
            <attribute>0</attribute>
            <order-direction>0</order-direction>
            <invisible-expression/>
            <disable-expression/>
            <category>基本信息</category>
            <fire-event>0</fire-event>
            <check-type>0</check-type>
            <real-type>7</real-type>
            <comment/>
            <validation/>
            <scope-permissions/>
            <properties/>
        </column>
        <column>
            <name>CXDDZY</name>
            <describe>持续督导专员</describe>
            <type>8</type>
            <biz-type>500</biz-type>
            <length>12</length>
            <scale>0</scale>
            <control>10</control>
            <primary-property>0</primary-property>
            <nullable>true</nullable>
            <unique>false</unique>
            <enabled>false</enabled>
            <visible>true</visible>
            <option/>
            <meta-column/>
            <ref-object>vUser_ZC</ref-object>
            <default>null</default>
            <attribute>0</attribute>
            <order-direction>0</order-direction>
            <expression/>
            <invisible-expression/>
            <disable-expression/>
            <category>基本信息</category>
            <fire-event>0</fire-event>
            <check-type>0</check-type>
            <real-type>6</real-type>
            <comment/>
            <validation/>
            <scope-permissions/>
            <properties/>
        </column>
        <column>
            <name>FKHFCS</name>
            <describe>反馈回复次数</describe>
            <type>8</type>
            <biz-type>200</biz-type>
            <length>10</length>
            <scale>0</scale>
            <control>1</control>
            <primary-property>0</primary-property>
            <nullable>false</nullable>
            <unique>false</unique>
            <enabled>false</enabled>
            <visible>true</visible>
            <option/>
            <meta-column/>
            <ref-object/>
            <default/>
            <attribute>0</attribute>
            <order-direction>0</order-direction>
            <expression/>
            <invisible-expression/>
            <disable-expression/>
            <category>基本信息</category>
            <fire-event>0</fire-event>
            <check-type>0</check-type>
            <real-type>1</real-type>
            <comment/>
            <validation/>
            <scope-permissions/>
            <properties>
                <ctrl-width>200</ctrl-width>
            </properties>
        </column>
        <column>
            <name>FKHFCJR</name>
            <describe>反馈回复出具日</describe>
            <type>8</type>
            <biz-type>300</biz-type>
            <length>8</length>
            <scale>0</scale>
            <control>3</control>
            <primary-property>0</primary-property>
            <nullable>false</nullable>
            <unique>false</unique>
            <enabled>false</enabled>
            <visible>true</visible>
            <option/>
            <meta-column/>
            <ref-object/>
            <default>null</default>
            <attribute>0</attribute>
            <order-direction>0</order-direction>
            <expression/>
            <invisible-expression/>
            <disable-expression/>
            <category>基本信息</category>
            <fire-event>0</fire-event>
            <check-type>0</check-type>
            <real-type>13</real-type>
            <comment/>
            <validation/>
            <scope-permissions/>
            <properties>
                <ctrl-width>200</ctrl-width>
            </properties>
        </column>
        <column>
            <name>SCDSHRQ</name>
            <describe>首次董事会日期</describe>
            <type>8</type>
            <biz-type>300</biz-type>
            <length>8</length>
            <scale>0</scale>
            <control>3</control>
            <primary-property>0</primary-property>
            <nullable>false</nullable>
            <unique>false</unique>
            <enabled>false</enabled>
            <visible>true</visible>
            <option/>
            <meta-column/>
            <ref-object/>
            <default>null</default>
            <attribute>0</attribute>
            <order-direction>0</order-direction>
            <expression/>
            <invisible-expression/>
            <disable-expression/>
            <category>基本信息</category>
            <fire-event>0</fire-event>
            <check-type>0</check-type>
            <real-type>13</real-type>
            <comment/>
            <validation/>
            <scope-permissions/>
            <properties>
                <ctrl-width>200</ctrl-width>
            </properties>
        </column>
        <column>
            <name>SFWCSJHPG</name>
            <describe>是否完成审计或评估</describe>
            <type>8</type>
            <biz-type>400</biz-type>
            <length>0</length>
            <scale>0</scale>
            <control>2</control>
            <primary-property>0</primary-property>
            <nullable>false</nullable>
            <unique>false</unique>
            <enabled>false</enabled>
            <visible>true</visible>
            <option>$D{JG_SF}</option>
            <meta-column/>
            <ref-object/>
            <default/>
            <attribute>0</attribute>
            <order-direction>0</order-direction>
            <invisible-expression/>
            <disable-expression/>
            <category>基本信息</category>
            <fire-event>0</fire-event>
            <check-type>0</check-type>
            <real-type>7</real-type>
            <comment/>
            <validation/>
            <scope-permissions/>
            <properties/>
        </column>
        <column>
            <name>XGZDCZQZLC</name>
            <describe>相关重大重组签章流程</describe>
            <type>8</type>
            <biz-type>500</biz-type>
            <length>0</length>
            <scale>0</scale>
            <control>10</control>
            <primary-property>0</primary-property>
            <nullable>true</nullable>
            <unique>false</unique>
            <enabled>false</enabled>
            <visible>true</visible>
            <option/>
            <meta-column/>
            <ref-object>lcIB_ZDZCCZSBQZLCB</ref-object>
            <default/>
            <attribute>0</attribute>
            <order-direction>0</order-direction>
            <invisible-expression/>
            <disable-expression/>
            <category>基本信息</category>
            <fire-event>0</fire-event>
            <check-type>0</check-type>
            <real-type>6</real-type>
            <comment/>
            <validation/>
            <constraint type="3">
                <SQL>["lcIB_ZDZCCZSBQZLCB.XMMC = {0}",[{"expression":"XMMC","scale":0,"length":0,"type":1}]]</SQL>
                <refColumns/>
            </constraint>
            <scope-permissions/>
            <properties/>
        </column>
        <column>
            <name>FJ</name>
            <describe>附件</describe>
            <type>8</type>
            <biz-type>700</biz-type>
            <length>0</length>
            <scale>0</scale>
            <control>12</control>
            <primary-property>0</primary-property>
            <nullable>true</nullable>
            <unique>false</unique>
            <enabled>false</enabled>
            <visible>true</visible>
            <option/>
            <ref-object>lcIB_ZDZCCZFKHFLCB_FJ</ref-object>
            <attribute>266240</attribute>
            <order-direction>0</order-direction>
            <category>需上传附件</category>
            <fire-event>0</fire-event>
            <check-type>0</check-type>
            <real-type>10</real-type>
            <properties/>
        </column>
        <column>
            <name>DBXZ</name>
            <describe>打包下载</describe>
            <type>8</type>
            <biz-type>100</biz-type>
            <length>200</length>
            <scale>0</scale>
            <control>16</control>
            <primary-property>8</primary-property>
            <nullable>true</nullable>
            <unique>false</unique>
            <enabled>true</enabled>
            <visible>true</visible>
            <attribute>262144</attribute>
            <order-direction>0</order-direction>
            <expression>&lt;%@ livebos language='javascript' %&gt;&#13;
var url='/gdlcDown?lcbdid='+ID+'&amp;insid='+InstID+'&amp;fjlx=1'+'&amp;yhid='+$Login.User;&#13;
 '&lt;input type="button" onclick=\'window.open("'+url+'")\' value="  打包下载  " /&gt;'&#13;
 //'&lt;a target=_blank href='+url+'&gt;&lt;font color=red&gt;下载&lt;/font&gt;&lt;/a&gt;'&#13;
</expression>
            <invisible-expression>&lt;%@ livebos language='javascript' %&gt;
LB.getClient().isStandard==false</invisible-expression>
            <category>需上传附件</category>
            <fire-event>0</fire-event>
            <check-type>0</check-type>
            <real-type>0</real-type>
            <properties/>
        </column>
        <column>
            <name>OASPXX</name>
            <describe>OA审批信息</describe>
            <type>8</type>
            <biz-type>100</biz-type>
            <length>500</length>
            <scale>0</scale>
            <control>16</control>
            <primary-property>8</primary-property>
            <nullable>true</nullable>
            <unique>false</unique>
            <enabled>true</enabled>
            <visible>true</visible>
            <option/>
            <meta-column/>
            <ref-object/>
            <default/>
            <attribute>4096</attribute>
            <order-direction>0</order-direction>
            <expression>&lt;%@ livebos language='javascript' %&gt;
var oaid=ABS_SQLVALUE("select nvl(max(oaworkflowid),0) from ecif.tib_oawfhandle where lcbd='lcIB_ZDZCCZFKHFLCB' and lcbdid=?",[ID])
var varSrc="/bss/ibb/nworkflow/page/oAsuggestion.sdo?oaWorkId="+oaid+"&amp;lcbd=lcIB_ZDZCCZFKHFLCB&amp;lcbdId="+ID;
"&lt;iframe id='lc_oayj' frameborder='0' width='100%' height='100%' scrolling='no' src='"+varSrc+"'&gt;&lt;/iframe&gt;"
 </expression>
            <invisible-expression>&lt;%@ livebos language='javascript' %&gt;
var oaid=ABS_SQLVALUE("select nvl(max(oaworkflowid),0) from ecif.tib_oawfhandle where lcbd='lcIB_GS_SBCLSH' and lcbdid=?",[ID])
oaid&lt;=0 </invisible-expression>
            <disable-expression/>
            <category>OA审批信息</category>
            <fire-event>0</fire-event>
            <check-type>0</check-type>
            <real-type>0</real-type>
            <comment/>
            <validation/>
            <scope-permissions/>
            <properties/>
        </column>
    </columns>
    <restrictions>
        <condition>{"statement":"lcIB_ZDZCCZFKHFLCB.SQR={0} and exists(select 1 from jgcrm.OS_WFENTRY where id=lcIB_ZDZCCZFKHFLCB.InstID and state&lt;&gt;3) or {0}=0","args":[{"expression":"$Login.User","scale":0,"length":0,"type":1}],"type":0}</condition>
    </restrictions>
    <display-options>
        <commands>
            <command type="5">
                <describe>查看</describe>
                <define>
                    <item>lcIB_ZDZCCZFKHFLCB_CK</item>
                </define>
                <is-default>1</is-default>
                <attribute>0</attribute>
                <icon-cls>lb-cmd-1</icon-cls>
            </command>
        </commands>
        <relations/>
    </display-options>
    <methods/>
    <properties>
        <property>
            <name>73</name>
            <value>SQR</value>
            <value>SQBM</value>
            <value>SQSJ</value>
            <value>LCBH</value>
            <value>GWZT</value>
            <value>LCBT</value>
            <value>GWZW</value>
            <value>BZ</value>
            <value>XMMC</value>
            <value>KHQC</value>
            <value>SSXT</value>
            <value>CXDDZY</value>
            <value>FKHFCS</value>
            <value>FKHFCJR</value>
            <value>SCDSHRQ</value>
            <value>SFWCSJHPG</value>
            <value>XGZDCZQZLC</value>
            <value>WF_STATE</value>
            <value>WF_CURRENTSTEPS</value>
        </property>
    </properties>
    <orders/>
    <panels/>
    <extend-buttons/>
</object>
