<?xml version="1.0" encoding="GB2312" standalone="no"?>
<object create-date="2017.08.31 14:12:46" creator="zhong.apex" flag="0" modifier="null" modify-date="null" name="vIB_BNBGZJYBAJZJZYLCB" object-id="d2a39b3e-c85d-4aef-8eb5-e8df075457a0" package="100_新三板.持续督导阶段定期工作流程.02-1-半年报工作简易备案及资金占用流程" type="1" version="1.0">
    <describe>半年报工作简易备案及资金占用流程</describe>
    <comment/>
    <datasource-name>ECIF</datasource-name>
    <parent>lcIB_BNBGZJYBAJZJZYLCB</parent>
    <attribute>268437520</attribute>
    <templet>默认</templet>
    <parameters/>
    <columns>
        <column>
            <name>ID</name>
            <describe>ID</describe>
            <type>8</type>
            <biz-type>100</biz-type>
            <length>0</length>
            <scale>0</scale>
            <control>0</control>
            <primary-property>0</primary-property>
            <nullable>false</nullable>
            <unique>false</unique>
            <enabled>false</enabled>
            <visible>false</visible>
            <option/>
            <meta-column/>
            <ref-object/>
            <default/>
            <attribute>0</attribute>
            <order-direction>0</order-direction>
            <expression/>
            <invisible-expression/>
            <disable-expression/>
            <category/>
            <fire-event>0</fire-event>
            <check-type>0</check-type>
            <real-type>0</real-type>
            <comment/>
            <validation/>
            <scope-permissions/>
        </column>
        <column>
            <name>InstID</name>
            <describe>InstID</describe>
            <type>8</type>
            <biz-type>100</biz-type>
            <length>0</length>
            <scale>0</scale>
            <control>0</control>
            <primary-property>0</primary-property>
            <nullable>false</nullable>
            <unique>false</unique>
            <enabled>true</enabled>
            <visible>true</visible>
            <option/>
            <meta-column/>
            <ref-object/>
            <default/>
            <attribute>0</attribute>
            <order-direction>0</order-direction>
            <expression/>
            <invisible-expression/>
            <disable-expression/>
            <category/>
            <fire-event>0</fire-event>
            <check-type>0</check-type>
            <real-type>0</real-type>
            <comment/>
            <validation/>
            <scope-permissions/>
        </column>
        <column>
            <name>SQR</name>
            <describe>申请人</describe>
            <type>8</type>
            <biz-type>100</biz-type>
            <length>0</length>
            <scale>0</scale>
            <control>10</control>
            <primary-property>0</primary-property>
            <nullable>false</nullable>
            <unique>false</unique>
            <enabled>false</enabled>
            <visible>true</visible>
            <option/>
            <meta-column/>
            <ref-object>tUser</ref-object>
            <default>$Login.User</default>
            <attribute>0</attribute>
            <order-direction>0</order-direction>
            <expression/>
            <invisible-expression/>
            <disable-expression/>
            <category>申请信息</category>
            <fire-event>0</fire-event>
            <check-type>0</check-type>
            <real-type>0</real-type>
            <comment/>
            <validation/>
            <scope-permissions/>
        </column>
        <column>
            <name>SQBM</name>
            <describe>申请部门</describe>
            <type>8</type>
            <biz-type>100</biz-type>
            <length>0</length>
            <scale>0</scale>
            <control>10</control>
            <primary-property>0</primary-property>
            <nullable>false</nullable>
            <unique>false</unique>
            <enabled>false</enabled>
            <visible>true</visible>
            <option/>
            <meta-column/>
            <ref-object>lbOrganization</ref-object>
            <default>$Login.User.OrgID</default>
            <attribute>0</attribute>
            <order-direction>0</order-direction>
            <expression/>
            <invisible-expression/>
            <disable-expression/>
            <category>申请信息</category>
            <fire-event>0</fire-event>
            <check-type>0</check-type>
            <real-type>0</real-type>
            <comment/>
            <validation/>
            <scope-permissions/>
        </column>
        <column>
            <name>SQSJ</name>
            <describe>申请时间</describe>
            <type>8</type>
            <biz-type>100</biz-type>
            <length>0</length>
            <scale>0</scale>
            <control>37</control>
            <primary-property>0</primary-property>
            <nullable>true</nullable>
            <unique>false</unique>
            <enabled>false</enabled>
            <visible>true</visible>
            <option/>
            <meta-column/>
            <ref-object/>
            <default>$DateTime.Now</default>
            <attribute>4</attribute>
            <order-direction>2</order-direction>
            <expression/>
            <invisible-expression/>
            <disable-expression/>
            <category>申请信息</category>
            <fire-event>0</fire-event>
            <check-type>0</check-type>
            <real-type>0</real-type>
            <comment/>
            <validation/>
            <scope-permissions/>
        </column>
        <column>
            <name>LCBH</name>
            <describe>流程编号</describe>
            <type>8</type>
            <biz-type>100</biz-type>
            <length>0</length>
            <scale>0</scale>
            <control>1</control>
            <primary-property>0</primary-property>
            <nullable>true</nullable>
            <unique>false</unique>
            <enabled>false</enabled>
            <visible>true</visible>
            <option/>
            <meta-column/>
            <ref-object/>
            <default/>
            <attribute>0</attribute>
            <order-direction>0</order-direction>
            <expression/>
            <invisible-expression/>
            <disable-expression/>
            <category>申请信息</category>
            <fire-event>0</fire-event>
            <check-type>0</check-type>
            <real-type>0</real-type>
            <comment/>
            <validation/>
            <scope-permissions/>
        </column>
        <column>
            <name>OLDBH</name>
            <describe>老系统编号</describe>
            <type>8</type>
            <biz-type>100</biz-type>
            <length>0</length>
            <scale>0</scale>
            <control>0</control>
            <primary-property>0</primary-property>
            <nullable>true</nullable>
            <unique>false</unique>
            <enabled>false</enabled>
            <visible>false</visible>
            <option/>
            <meta-column/>
            <ref-object/>
            <default/>
            <attribute>0</attribute>
            <order-direction>0</order-direction>
            <expression/>
            <invisible-expression/>
            <disable-expression/>
            <category>申请信息</category>
            <fire-event>0</fire-event>
            <check-type>0</check-type>
            <real-type>0</real-type>
            <comment/>
            <validation/>
            <scope-permissions/>
        </column>
        <column>
            <name>LCBT</name>
            <describe>流程标题</describe>
            <type>8</type>
            <biz-type>100</biz-type>
            <length>0</length>
            <scale>0</scale>
            <control>1</control>
            <primary-property>0</primary-property>
            <nullable>false</nullable>
            <unique>false</unique>
            <enabled>false</enabled>
            <visible>true</visible>
            <option/>
            <meta-column/>
            <ref-object/>
            <default/>
            <attribute>4098</attribute>
            <order-direction>0</order-direction>
            <expression/>
            <invisible-expression/>
            <disable-expression/>
            <category>基本信息</category>
            <fire-event>0</fire-event>
            <check-type>0</check-type>
            <real-type>0</real-type>
            <comment/>
            <validation/>
            <scope-permissions/>
        </column>
        <column>
            <name>XMMC</name>
            <describe>项目名称</describe>
            <type>8</type>
            <biz-type>100</biz-type>
            <length>0</length>
            <scale>0</scale>
            <control>10</control>
            <primary-property>0</primary-property>
            <nullable>false</nullable>
            <unique>false</unique>
            <enabled>false</enabled>
            <visible>true</visible>
            <option/>
            <meta-column/>
            <ref-object>VIB_XMXX_XSB_WD</ref-object>
            <default/>
            <attribute>67108864</attribute>
            <order-direction>0</order-direction>
            <expression/>
            <invisible-expression/>
            <disable-expression/>
            <category>基本信息</category>
            <fire-event>0</fire-event>
            <check-type>0</check-type>
            <real-type>0</real-type>
            <comment/>
            <validation/>
            <scope-permissions/>
        </column>
        <column>
            <name>SM</name>
            <describe>说明</describe>
            <type>8</type>
            <biz-type>100</biz-type>
            <length>0</length>
            <scale>0</scale>
            <control>16</control>
            <primary-property>0</primary-property>
            <nullable>true</nullable>
            <unique>false</unique>
            <enabled>true</enabled>
            <visible>true</visible>
            <option/>
            <meta-column/>
            <ref-object/>
            <default/>
            <attribute>266240</attribute>
            <order-direction>0</order-direction>
            <expression/>
            <invisible-expression>&lt;%@ livebos language='javascript' %&gt;
XMMC.SFFXXM!=1 </invisible-expression>
            <disable-expression/>
            <category>基本信息</category>
            <fire-event>0</fire-event>
            <check-type>0</check-type>
            <real-type>0</real-type>
            <comment/>
            <validation/>
            <scope-permissions/>
        </column>
        <column>
            <name>CXDDRQ</name>
            <describe>持续督导日期</describe>
            <type>8</type>
            <biz-type>100</biz-type>
            <length>0</length>
            <scale>0</scale>
            <control>3</control>
            <primary-property>0</primary-property>
            <nullable>true</nullable>
            <unique>false</unique>
            <enabled>false</enabled>
            <visible>true</visible>
            <option/>
            <meta-column/>
            <ref-object/>
            <default>null</default>
            <attribute>0</attribute>
            <order-direction>0</order-direction>
            <expression/>
            <invisible-expression/>
            <disable-expression/>
            <category>基本信息</category>
            <fire-event>0</fire-event>
            <check-type>0</check-type>
            <real-type>0</real-type>
            <comment/>
            <validation/>
            <scope-permissions/>
            <properties>
                <ctrl-width>200</ctrl-width>
            </properties>
        </column>
        <column>
            <name>CXDDZY</name>
            <describe>持续督导专员</describe>
            <type>8</type>
            <biz-type>100</biz-type>
            <length>0</length>
            <scale>0</scale>
            <control>10</control>
            <primary-property>0</primary-property>
            <nullable>true</nullable>
            <unique>false</unique>
            <enabled>false</enabled>
            <visible>true</visible>
            <option/>
            <meta-column/>
            <ref-object>vUser_ZC</ref-object>
            <default>null</default>
            <attribute>0</attribute>
            <order-direction>0</order-direction>
            <expression/>
            <invisible-expression/>
            <disable-expression/>
            <category>基本信息</category>
            <fire-event>0</fire-event>
            <check-type>0</check-type>
            <real-type>0</real-type>
            <comment/>
            <validation/>
            <scope-permissions/>
        </column>
        <column>
            <name>BNBNPLRQ</name>
            <describe>半年报拟披露日期</describe>
            <type>8</type>
            <biz-type>100</biz-type>
            <length>0</length>
            <scale>0</scale>
            <control>3</control>
            <primary-property>0</primary-property>
            <nullable>false</nullable>
            <unique>false</unique>
            <enabled>false</enabled>
            <visible>true</visible>
            <option/>
            <meta-column/>
            <ref-object/>
            <default>null</default>
            <attribute>0</attribute>
            <order-direction>0</order-direction>
            <expression/>
            <invisible-expression/>
            <disable-expression/>
            <category>基本信息</category>
            <fire-event>0</fire-event>
            <check-type>0</check-type>
            <real-type>0</real-type>
            <comment/>
            <validation/>
            <scope-permissions/>
            <properties>
                <ctrl-width>200</ctrl-width>
            </properties>
        </column>
        <column>
            <name>MJZJSYGLCZWT</name>
            <describe>募集资金使用管理存在问题</describe>
            <type>8</type>
            <biz-type>100</biz-type>
            <length>0</length>
            <scale>0</scale>
            <control>5</control>
            <primary-property>0</primary-property>
            <nullable>false</nullable>
            <unique>false</unique>
            <enabled>false</enabled>
            <visible>true</visible>
            <option>1|是;0|否;2|不适用</option>
            <meta-column/>
            <ref-object/>
            <default>null</default>
            <attribute>0</attribute>
            <order-direction>0</order-direction>
            <expression/>
            <invisible-expression/>
            <disable-expression/>
            <category>基本信息</category>
            <fire-event>0</fire-event>
            <check-type>0</check-type>
            <real-type>0</real-type>
            <comment/>
            <validation/>
            <scope-permissions/>
            <properties>
                <ctrl-width>200</ctrl-width>
            </properties>
        </column>
        <column>
            <name>FXMS</name>
            <describe>风险描述</describe>
            <type>8</type>
            <biz-type>100</biz-type>
            <length>0</length>
            <scale>0</scale>
            <control>7</control>
            <primary-property>0</primary-property>
            <nullable>false</nullable>
            <unique>false</unique>
            <enabled>false</enabled>
            <visible>true</visible>
            <option/>
            <meta-column/>
            <ref-object/>
            <default/>
            <attribute>4096</attribute>
            <order-direction>0</order-direction>
            <expression/>
            <invisible-expression>&lt;%@ livebos language='javascript' %&gt;
MJZJSYGLCZWT!=1 </invisible-expression>
            <disable-expression/>
            <category>基本信息</category>
            <fire-event>0</fire-event>
            <check-type>0</check-type>
            <real-type>0</real-type>
            <comment/>
            <validation/>
            <scope-permissions/>
        </column>
        <column>
            <name>BNBPLRQ</name>
            <describe>半年报披露日期</describe>
            <type>8</type>
            <biz-type>100</biz-type>
            <length>0</length>
            <scale>0</scale>
            <control>3</control>
            <primary-property>0</primary-property>
            <nullable>false</nullable>
            <unique>false</unique>
            <enabled>false</enabled>
            <visible>true</visible>
            <option/>
            <meta-column/>
            <ref-object/>
            <default>null</default>
            <attribute>0</attribute>
            <order-direction>0</order-direction>
            <expression/>
            <invisible-expression/>
            <disable-expression/>
            <category>基本信息</category>
            <fire-event>0</fire-event>
            <check-type>0</check-type>
            <real-type>0</real-type>
            <comment/>
            <validation/>
            <scope-permissions/>
            <properties>
                <ctrl-width>200</ctrl-width>
            </properties>
        </column>
        <column>
            <name>SFZJZY</name>
            <describe>是否资金占用</describe>
            <type>8</type>
            <biz-type>100</biz-type>
            <length>0</length>
            <scale>0</scale>
            <control>2</control>
            <primary-property>0</primary-property>
            <nullable>false</nullable>
            <unique>false</unique>
            <enabled>false</enabled>
            <visible>true</visible>
            <option>$D{JG_SF}</option>
            <meta-column/>
            <ref-object/>
            <default/>
            <attribute>0</attribute>
            <order-direction>0</order-direction>
            <expression/>
            <invisible-expression/>
            <disable-expression/>
            <category>基本信息</category>
            <fire-event>0</fire-event>
            <check-type>0</check-type>
            <real-type>0</real-type>
            <comment/>
            <validation/>
            <scope-permissions/>
            <properties>
                <ctrl-width>200</ctrl-width>
            </properties>
        </column>
        <column>
            <name>FJ</name>
            <describe>附件</describe>
            <type>8</type>
            <biz-type>100</biz-type>
            <length>0</length>
            <scale>0</scale>
            <control>12</control>
            <primary-property>0</primary-property>
            <nullable>true</nullable>
            <unique>false</unique>
            <enabled>false</enabled>
            <visible>true</visible>
            <option/>
            <meta-column/>
            <ref-object>lcIB_BNBGZJYBAJZJZYLCB_FJ</ref-object>
            <default/>
            <attribute>266240</attribute>
            <order-direction>0</order-direction>
            <expression/>
            <invisible-expression/>
            <disable-expression/>
            <category>需上传附件</category>
            <fire-event>0</fire-event>
            <check-type>0</check-type>
            <real-type>0</real-type>
            <comment/>
            <validation/>
            <scope-permissions/>
        </column>
        <column>
            <name>DBXZ</name>
            <describe>打包下载</describe>
            <type>8</type>
            <biz-type>100</biz-type>
            <length>0</length>
            <scale>0</scale>
            <control>16</control>
            <primary-property>0</primary-property>
            <nullable>true</nullable>
            <unique>false</unique>
            <enabled>true</enabled>
            <visible>true</visible>
            <option/>
            <meta-column/>
            <ref-object/>
            <default/>
            <attribute>262144</attribute>
            <order-direction>0</order-direction>
            <expression/>
            <invisible-expression>&lt;%@ livebos language='javascript' %&gt;
LB.getClient().isStandard==false </invisible-expression>
            <disable-expression/>
            <category>需上传附件</category>
            <fire-event>0</fire-event>
            <check-type>0</check-type>
            <real-type>0</real-type>
            <comment/>
            <validation/>
            <scope-permissions/>
        </column>
        <column>
            <name>ZJZYQK</name>
            <describe>资金占用情况</describe>
            <type>8</type>
            <biz-type>100</biz-type>
            <length>0</length>
            <scale>0</scale>
            <control>12</control>
            <primary-property>0</primary-property>
            <nullable>false</nullable>
            <unique>false</unique>
            <enabled>false</enabled>
            <visible>true</visible>
            <option/>
            <meta-column/>
            <ref-object>lcIB_BNBGZJYBAJZJZYLCB_ZJZY</ref-object>
            <default/>
            <attribute>266240</attribute>
            <order-direction>0</order-direction>
            <expression/>
            <invisible-expression>&lt;%@ livebos language='javascript' %&gt;
SFZJZY!=1 </invisible-expression>
            <disable-expression/>
            <category>资金占用情况</category>
            <fire-event>0</fire-event>
            <check-type>0</check-type>
            <real-type>0</real-type>
            <comment/>
            <validation/>
            <scope-permissions/>
        </column>
        <column>
            <name>CXDDZYB</name>
            <describe>持续督导B岗</describe>
            <type>8</type>
            <biz-type>100</biz-type>
            <length>0</length>
            <scale>0</scale>
            <control>10</control>
            <primary-property>0</primary-property>
            <nullable>false</nullable>
            <unique>false</unique>
            <enabled>true</enabled>
            <visible>true</visible>
            <option/>
            <meta-column/>
            <ref-object>vUser_ZC</ref-object>
            <default>null</default>
            <attribute>0</attribute>
            <order-direction>0</order-direction>
            <expression/>
            <invisible-expression/>
            <disable-expression/>
            <category>基本信息</category>
            <fire-event>0</fire-event>
            <check-type>0</check-type>
            <real-type>0</real-type>
            <comment/>
            <validation/>
            <scope-permissions/>
        </column>
    </columns>
    <restrictions>
        <condition/>
    </restrictions>
    <display-options>
        <commands>
            <command type="5">
                <describe>查看</describe>
                <define>
                    <item>lcIB_BNBGZJYBAJZJZYLCB_CK</item>
                </define>
                <is-default>1</is-default>
                <attribute>2</attribute>
                <icon-cls>lb-cmd-1</icon-cls>
                <tip/>
            </command>
            <command type="2">
                <describe>流程跟踪</describe>
                <define>
                    <item>vIB_BNBGZJYBAJZJZYLCB</item>
                    <item>TrackWork</item>
                </define>
                <is-default>2</is-default>
                <attribute>0</attribute>
                <icon-cls/>
                <tip/>
            </command>
        </commands>
        <relations/>
    </display-options>
    <methods/>
    <properties>
        <property>
            <name>73</name>
            <value>SQR</value>
            <value>SQBM</value>
            <value>SQSJ</value>
            <value>LCBH</value>
            <value>XMMC</value>
            <value>CXDDRQ</value>
            <value>CXDDZY</value>
            <value>BNBNPLRQ</value>
            <value>FXMS</value>
            <value>BNBPLRQ</value>
            <value>MJZJSYGLCZWT</value>
            <value>SFZJZY</value>
            <value>ZJZYQK</value>
            <value>WF_STATE</value>
            <value>WF_CURRENTSTEPS</value>
        </property>
    </properties>
    <orders/>
    <panels/>
    <extend-buttons/>
</object>
